google/cloud/recommendationengine/__init__.py
google/cloud/recommendationengine/gapic_version.py
google/cloud/recommendationengine/py.typed
google/cloud/recommendationengine_v1beta1/__init__.py
google/cloud/recommendationengine_v1beta1/gapic_metadata.json
google/cloud/recommendationengine_v1beta1/gapic_version.py
google/cloud/recommendationengine_v1beta1/py.typed
google/cloud/recommendationengine_v1beta1/services/__init__.py
google/cloud/recommendationengine_v1beta1/services/catalog_service/__init__.py
google/cloud/recommendationengine_v1beta1/services/catalog_service/async_client.py
google/cloud/recommendationengine_v1beta1/services/catalog_service/client.py
google/cloud/recommendationengine_v1beta1/services/catalog_service/pagers.py
google/cloud/recommendationengine_v1beta1/services/catalog_service/transports/__init__.py
google/cloud/recommendationengine_v1beta1/services/catalog_service/transports/base.py
google/cloud/recommendationengine_v1beta1/services/catalog_service/transports/grpc.py
google/cloud/recommendationengine_v1beta1/services/catalog_service/transports/grpc_asyncio.py
google/cloud/recommendationengine_v1beta1/services/catalog_service/transports/rest.py
google/cloud/recommendationengine_v1beta1/services/catalog_service/transports/rest_base.py
google/cloud/recommendationengine_v1beta1/services/prediction_api_key_registry/__init__.py
google/cloud/recommendationengine_v1beta1/services/prediction_api_key_registry/async_client.py
google/cloud/recommendationengine_v1beta1/services/prediction_api_key_registry/client.py
google/cloud/recommendationengine_v1beta1/services/prediction_api_key_registry/pagers.py
google/cloud/recommendationengine_v1beta1/services/prediction_api_key_registry/transports/__init__.py
google/cloud/recommendationengine_v1beta1/services/prediction_api_key_registry/transports/base.py
google/cloud/recommendationengine_v1beta1/services/prediction_api_key_registry/transports/grpc.py
google_cloud_recommendations_ai-0.11.0.dist-info/licenses/LICENSE
google_cloud_recommendations_ai-0.11.0.dist-info/METADATA
google_cloud_recommendations_ai-0.11.0.dist-info/WHEEL
google_cloud_recommendations_ai-0.11.0.dist-info/top_level.txt
google_cloud_recommendations_ai-0.11.0.dist-info/RECORD
